iut_pe/__init__.py
iut_pe/helpers.py
iut_pe/scripts.py
iut_pe/static/template.tex
iut_pe-0.1.8.dist-info/LICENSE
iut_pe-0.1.8.dist-info/METADATA
iut_pe-0.1.8.dist-info/WHEEL
iut_pe-0.1.8.dist-info/entry_points.txt
iut_pe-0.1.8.dist-info/RECORD
