Metadata-Version: 2.1
Name: iut-pe
Version: 0.1.8
Summary: Outil de création de fiches de poursuites d'études lié à ScoDoc
Home-page: https://gricad-gitlab.univ-grenoble-alpes.fr/roubine/iut-pe
License: LICENSE
Keywords: BUT,Poursuites d'études
Author: Emmanuel Roubin
Author-email: emmanuel.roubin@univ-grenoble-alpes.fr
Maintainer: Emmanuel Roubin
Maintainer-email: emmanuel.roubin@univ-grenoble-alpes.fr
Requires-Python: >=3.8.1,<4.0.0
Classifier: License :: Other/Proprietary License
Classifier: License :: Public Domain
Classifier: Natural Language :: French
Classifier: Programming Language :: Python :: 3
Classifier: Programming Language :: Python :: 3.9
Classifier: Programming Language :: Python :: 3.10
Classifier: Programming Language :: Python :: 3.11
Classifier: Programming Language :: Python :: 3.12
Requires-Dist: pyyaml
Requires-Dist: requests
Project-URL: Repository, https://gricad-gitlab.univ-grenoble-alpes.fr/roubine/iut-pe
